gl_pages_forward/__init__.py
gl_pages_forward/main.py
gl_pages_forward/rsc/__init__.py
gl_pages_forward/rsc/index.html.j2
gl_pages_forward/rsc/overview.html.j2
gl_pages_forward/tests/__init__.py
gl_pages_forward/tests/config.yml
gl_pages_forward-0.1.3.dist-info/entry_points.txt
gl_pages_forward-0.1.3.dist-info/LICENSE
gl_pages_forward-0.1.3.dist-info/WHEEL
gl_pages_forward-0.1.3.dist-info/METADATA
gl_pages_forward-0.1.3.dist-info/RECORD
