Metadata-Version: 2.1
Name: gl-pages-forward
Version: 0.1.3
Summary: Script to create forward pages.
Home-page: https://github.com/pstoeckle/GitLab-Forward-Pages.git
License: Apache-2.0
Author: Patrick Stöckle
Author-email: patrick.stoeckle@posteo.de
Maintainer: Patrick Stöckle
Maintainer-email: patrick.stoeckle@posteo.de
Requires-Python: >=3.7,<4.0
Classifier: License :: OSI Approved :: Apache Software License
Classifier: Programming Language :: Python :: 3
Classifier: Programming Language :: Python :: 3.7
Classifier: Programming Language :: Python :: 3.8
Classifier: Programming Language :: Python :: 3.9
Classifier: Programming Language :: Python :: 3.10
Classifier: Programming Language :: Python :: 3.11
Requires-Dist: Jinja2 (>=3.1.2,<4.0.0)
Requires-Dist: minify-html (>=0.10.3,<0.11.0)
Requires-Dist: ruamel.yaml (>=0.17.21,<0.18.0)
Requires-Dist: typer (>=0.7.0,<0.8.0)
Project-URL: Repository, https://github.com/pstoeckle/GitLab-Forward-Pages.git
